{"id":"bdf34e3d-8e26-4060-9c24-c3bff345c94a","revision":0,"last_node_id":49,"last_link_id":76,"nodes":[{"id":9,"type":"SaveImage","pos":[401.00005352722997,54.00003772834776],"size":[530,480],"flags":{},"order":8,"mode":0,"inputs":[{"localized_name":"images","name":"images","type":"IMAGE","link":70},{"localized_name":"préfixe_du_nom_de_fichier","name":"filename_prefix","type":"STRING","widget":{"name":"filename_prefix"},"link":null}],"outputs":[],"properties":{"Node name for S&R":"SaveImage","enableTabs":false,"tabWidth":65,"tabXOffset":10,"hasSecondTab":false,"secondTabText":"Send Back","secondTabOffset":80,"secondTabWidth":65,"cnr_id":"comfy-core","ver":"0.5.1"},"widgets_values":["NewBie-Image-Exp0.1"]},{"id":47,"type":"PrimitiveStringMultiline","pos":[-708.9999893301433,54.00003772834776],"size":[400,200],"flags":{},"order":0,"mode":0,"inputs":[{"localized_name":"valeur","name":"value","type":"STRING","widget":{"name":"value"},"link":null}],"outputs":[{"localized_name":"CHAÎNE","name":"STRING","type":"STRING","links":[71]}],"title":"Prompt Template","properties":{"Node name for S&R":"PrimitiveStringMultiline","enableTabs":false,"tabWidth":65,"tabXOffset":10,"hasSecondTab":false,"secondTabText":"Send Back","secondTabOffset":80,"secondTabWidth":65,"cnr_id":"comfy-core","ver":"0.5.1"},"widgets_values":["You are an assistant designed to generate high-quality anime images with the highest degree of image-text alignment based on xml format textual prompts. <Prompt Start>\n{\n\"character_1\": {\n\"bbox\": [\n0,\n0,\n1000,\n1000\n],\n\"name\": \"$character_1$\"\n},\n\"image\": {\n\"tags\": \"\n{user_prompt}\n\",\n\"caption\": \"{caption}\"\n}\n}"]},{"id":46,"type":"StringReplace","pos":[-269.00001600305325,364.0000646063011],"size":[210,34],"flags":{"collapsed":true},"order":6,"mode":0,"inputs":[{"localized_name":"chaîne","name":"string","type":"STRING","widget":{"name":"string"},"link":73},{"localized_name":"rechercher","name":"find","type":"STRING","widget":{"name":"find"},"link":null},{"localized_name":"remplacer","name":"replace","type":"STRING","widget":{"name":"replace"},"link":74}],"outputs":[{"localized_name":"CHAÎNE","name":"STRING","type":"STRING","links":[76]}],"properties":{"Node name for S&R":"StringReplace","enableTabs":false,"tabWidth":65,"tabXOffset":10,"hasSecondTab":false,"secondTabText":"Send Back","secondTabOffset":80,"secondTabWidth":65,"cnr_id":"comfy-core","ver":"0.5.1"},"widgets_values":["","{caption}",""]},{"id":44,"type":"PrimitiveStringMultiline","pos":[-708.9999893301433,684.000141921251],"size":[400,340],"flags":{"collapsed":false},"order":1,"mode":0,"inputs":[{"localized_name":"valeur","name":"value","type":"STRING","widget":{"name":"value"},"link":null}],"outputs":[{"localized_name":"CHAÎNE","name":"STRING","type":"STRING","links":[74]}],"title":"Caption","properties":{"Node name for S&R":"PrimitiveStringMultiline","enableTabs":false,"tabWidth":65,"tabXOffset":10,"hasSecondTab":false,"secondTabText":"Send Back","secondTabOffset":80,"secondTabWidth":65,"cnr_id":"comfy-core","ver":"0.5.1"},"widgets_values":["An extremely detailed, vibrant, and dynamic digital illustration in an anime style features a young girl, identified as $character_1$, in an extreme close-up, tight shot, captured with a dramatic Dutch angle[cite: 36, 38]. $Character_1$, who resembles Roxy Migurdia, is positioned to fill the entire frame in the center-foreground, creating an intense, immersive perspective[cite: 15, 32]. She has long, bright **blue hair** that appears to be floating dynamically around her head and shoulders, with a small **ahoge** visible on top[cite: 31, 32]. Her intense, **concerned blue eyes** with sharp pupils stare directly out of the frame toward the viewer, conveying a serious and focused expression, categorized as **jitome**[cite: 31, 34]. The top half of her face is obscured by a shadow cast by her very large, wide-brimmed **black witch hat**, creating a dramatic **cut light** effect that enhances the intense atmosphere and contributes to her shaded face[cite: 36, 37]. She is wearing a complex, **multicolored outfit** that includes a high-collared garment, possibly a coat or shawl, over what appears to be a **white and blue dress** with intricate trim, suggesting a magical or fantasy setting[cite: 31]. The clothing is obscured in parts by the surrounding special effects[cite: 38]. Her action is highly dynamic: her left arm extends dramatically out of the image plane, with her **hand open and pointing towards the camera**[cite: 32]. Her right hand is used to hold or adjust the brim of the large hat on her head[cite: 32]. The entire scene is enveloped in a powerful, dynamic effect of **fluid dynamics** and a **vortex**[cite: 36, 38]. **Cerulean blue water, or fluid**, is spiraling and swirling around her body and hand, creating a **three-dimensional spiral structure** that dominates the composition[cite: 38]. Scattered among the fluid are multiple sharp, glowing **blue crystal petals** and shards, giving the scene a magical and crystalline quality[cite: 37, 38]. The art style is defined by high resolution, best quality, and master-level detail, with noticeable artistic effects such as **chromatic aberration** and **bokeh** enhancing the sense of motion and depth[cite: 37]. The dark, abstract background further emphasizes the character and the vibrant blue light of the surrounding magical effects[cite: 36]. The lighting is highly dramatic, with a strong, artificial light source highlighting the crystalline fluids and the bottom of her face[cite: 37]. This is an illustration with an epic composition[cite: 36]."]},{"id":41,"type":"200c18f2-7c51-4b4a-bf17-293f2f691b1b","pos":[-68.99995290554648,54.00003772834776],"size":[440,440],"flags":{},"order":7,"mode":0,"inputs":[{"name":"text","type":"STRING","widget":{"name":"text"},"link":76},{"name":"text_1","type":"STRING","widget":{"name":"text_1"},"link":null}],"outputs":[{"localized_name":"IMAGE","name":"IMAGE","type":"IMAGE","links":[70]}],"properties":{"proxyWidgets":[["-1","text"],["-1","text_1"],["3","seed"],["3","control_after_generate"],["31","width"],["31","height"]],"enableTabs":false,"tabWidth":65,"tabXOffset":10,"hasSecondTab":false,"secondTabText":"Send Back","secondTabOffset":80,"secondTabWidth":65,"cnr_id":"comfy-core","ver":"0.5.1"},"widgets_values":["","You are an assistant designed to generate low-quality images based on textual prompts. <Prompt Start>"]},{"id":43,"type":"StringReplace","pos":[-269.00001600305325,314.00004883192446],"size":[210,34],"flags":{"collapsed":true},"order":5,"mode":0,"inputs":[{"localized_name":"chaîne","name":"string","type":"STRING","widget":{"name":"string"},"link":71},{"localized_name":"rechercher","name":"find","type":"STRING","widget":{"name":"find"},"link":null},{"localized_name":"remplacer","name":"replace","type":"STRING","widget":{"name":"replace"},"link":72}],"outputs":[{"localized_name":"CHAÎNE","name":"STRING","type":"STRING","links":[73]}],"properties":{"Node name for S&R":"StringReplace","enableTabs":false,"tabWidth":65,"tabXOffset":10,"hasSecondTab":false,"secondTabText":"Send Back","secondTabOffset":80,"secondTabWidth":65,"cnr_id":"comfy-core","ver":"0.5.1"},"widgets_values":["","{user_prompt}",""]},{"id":48,"type":"PrimitiveStringMultiline","pos":[-708.9999893301433,303.9999983949279],"size":[400,340],"flags":{},"order":2,"mode":0,"inputs":[{"localized_name":"valeur","name":"value","type":"STRING","widget":{"name":"value"},"link":null}],"outputs":[{"localized_name":"CHAÎNE","name":"STRING","type":"STRING","links":[72]}],"title":"User Prompt","properties":{"Node name for S&R":"PrimitiveStringMultiline","enableTabs":false,"tabWidth":65,"tabXOffset":10,"hasSecondTab":false,"secondTabText":"Send Back","secondTabOffset":80,"secondTabWidth":65,"cnr_id":"comfy-core","ver":"0.5.1"},"widgets_values":["<character_1>\n<n>$character_1$</n>\n<gender>1girl</gender>\n<appearance>blue hair, long hair, floating hair, ahoge, blue eyes, sharp pupils, fair skin, shaded face, beauty mark, Roxy Migurdia</appearance>\n<clothing>witch hat, large hat, black hat, shawl, coat, white and blue dress, multicolored clothing, high collar</clothing>\n<body_type>slender, small breasts</body_type>\n<expression>serious, concerned, concerned eyes, intense gaze, open mouth, slight frown, jitome</expression>\n<action>pointing at viewer, hand out, hand gesture, posing, head tilt, holding hat, supporting hat, dynamic pose, mid-action</action>\n<interaction>pointing towards the camera</interaction>\n<position>full-frame, center, foreground, tight shot, extreme close-up</position>\n</character_1>\n\n<general_tags>\n<count>1girl</count>\n<artists>yoneyama mai, Mika pikazo, Rolua</artists>\n<style>anime style, digital art, illustration, detailed shading, cut light, fluid dynamics, cerulean gold particle effects</style>\n<background>abstract, dark background, dynamic background</background>\n<environment>vortex, spiral, surrounded by floating crystal petals, caustics</environment>\n<perspective>dramatic angle, dutch angle, from below, tight shot, extreme close up</perspective>\n<atmosphere>intense, dynamic, magical, mysterious, epic composition, shaded</atmosphere>\n<lighting>cut light, shadow, strong contrast, dramatic lighting</lighting>\n<quality>masterpiece, best quality, very awa, newest, highres, absurdres, an extremely delicate and beautiful, original, illustration, amazing, detailed</quality>\n<objects>crystal, crystal petals</objects>\n<other>fluid dynamics, spiral, three-dimensional spiral structure, chromatic aberration, bokeh, floating, special effects covered in crystals and fluids obscure a part of the body</other>\n</general_tags>"]},{"id":37,"type":"MarkdownNote","pos":[-1170,260],"size":[430,719.296875],"flags":{},"order":3,"mode":0,"inputs":[],"outputs":[],"title":"For Local User","properties":{},"widgets_values":["Guide: [Subgraph](https://docs.comfy.org/interface/features/subgraph)\n\n## Report issue\n\nNote: please update ComfyUI first ([guide](https://docs.comfy.org/zh-CN/installation/update_comfyui)) and prepare required models. Desktop/Cloud ship stable builds; nightly-supported models may not be included yet, please wait for the next stable release.\n\n- Cannot run / runtime errors: [ComfyUI/issues](https://github.com/comfyanonymous/ComfyUI/issues)\n- UI / frontend issues: [ComfyUI_frontend/issues](https://github.com/Comfy-Org/ComfyUI_frontend/issues)\n- Workflow issues: [workflow_templates/issues](https://github.com/Comfy-Org/workflow_templates/issues)\n\n\n## Model links\n\n**text_encoders**\n\n- [gemma_3_4b_it_bf16.safetensors](https://huggingface.co/Comfy-Org/NewBie-image-Exp0.1_repackaged/resolve/main/split_files/text_encoders/gemma_3_4b_it_bf16.safetensors)\n- [jina_clip_v2_bf16.safetensors](https://huggingface.co/Comfy-Org/NewBie-image-Exp0.1_repackaged/resolve/main/split_files/text_encoders/jina_clip_v2_bf16.safetensors)\n\n**diffusion_models**\n\n- [NewBie-Image-Exp0.1-bf16.safetensors](https://huggingface.co/Comfy-Org/NewBie-image-Exp0.1_repackaged/resolve/main/split_files/diffusion_models/NewBie-Image-Exp0.1-bf16.safetensors)\n\n**vae**\n\n- [ae.safetensors](https://huggingface.co/Comfy-Org/z_image_turbo/resolve/main/split_files/vae/ae.safetensors)\n\n\nModel Storage Location\n\n```\n📂 ComfyUI/\n├── 📂 models/\n│   ├── 📂 text_encoders/\n│   │      ├── gemma_3_4b_it_bf16.safetensors\n│   │      └── jina_clip_v2_bf16.safetensors\n│   ├── 📂 diffusion_models/\n│   │      └── NewBie-Image-Exp0.1-bf16.safetensors\n│   └── 📂 vae/\n│          └── ae.safetensors\n```\n"],"color":"#432","bgcolor":"#000"},{"id":49,"type":"MarkdownNote","pos":[-1170,60],"size":[430,140],"flags":{},"order":4,"mode":0,"inputs":[],"outputs":[],"title":"About NewBie Exp0.1","properties":{},"widgets_values":["NewBie-image is an anime-style text-to-image generation model developed by NewBieAI Lab, built for creating high-quality anime and second-generation (ACG) images.\n\n- Huggingface: [NewBie-AI/NewBie-image-Exp0.1](https://huggingface.co/NewBie-AI/NewBie-image-Exp0.1)\n- [Getting Started Guide](https://ai.feishu.cn/wiki/NZl9wm7V1iuNzmkRKCUcb1USnsh)\n- [LoRa Trainer](https://www.notion.so/Newbie-AI-lora-training-tutorial-English-2c2e4ae984ab8177b312e318827657e6?source=copy_link)"],"color":"#432","bgcolor":"#000"}],"links":[[70,41,0,9,0,"IMAGE"],[71,47,0,43,0,"STRING"],[72,48,0,43,2,"STRING"],[73,43,0,46,0,"STRING"],[74,44,0,46,2,"STRING"],[76,46,0,41,0,"STRING"]],"groups":[],"definitions":{"subgraphs":[{"id":"200c18f2-7c51-4b4a-bf17-293f2f691b1b","version":1,"state":{"lastGroupId":0,"lastNodeId":52,"lastLinkId":87,"lastRerouteId":0},"revision":0,"config":{},"name":"NewBie Image Exp0.1","inputNode":{"id":-10,"bounding":[-270,322,120,80]},"outputNode":{"id":-20,"bounding":[1350,312,120,60]},"inputs":[{"id":"78101755-8120-46c2-ae17-b950d2916144","name":"text","type":"STRING","linkIds":[86],"pos":[-170,342]},{"id":"021d1121-626e-4a59-96ca-cd37149657c5","name":"text_1","type":"STRING","linkIds":[87],"pos":[-170,362]}],"outputs":[{"id":"6182559e-689f-4f99-9884-caa05370245d","name":"IMAGE","type":"IMAGE","linkIds":[9],"localized_name":"IMAGE","pos":[1370,332]}],"widgets":[],"nodes":[{"id":32,"type":"ModelSamplingAuraFlow","pos":[810,60],"size":[270,58],"flags":{},"order":4,"mode":0,"inputs":[{"localized_name":"modèle","name":"model","type":"MODEL","link":53},{"localized_name":"décalage","name":"shift","type":"FLOAT","widget":{"name":"shift"},"link":null}],"outputs":[{"localized_name":"MODÈLE","name":"MODEL","type":"MODEL","links":[50]}],"properties":{"Node name for S&R":"ModelSamplingAuraFlow","enableTabs":false,"tabWidth":65,"tabXOffset":10,"hasSecondTab":false,"secondTabText":"Send Back","secondTabOffset":80,"secondTabWidth":65,"cnr_id":"comfy-core","ver":"0.5.1"},"widgets_values":[6]},{"id":30,"type":"UNETLoader","pos":[-90,70],"size":[370,82],"flags":{},"order":0,"mode":0,"inputs":[{"localized_name":"nom_unet","name":"unet_name","type":"COMBO","widget":{"name":"unet_name"},"link":null},{"localized_name":"dtype_poids","name":"weight_dtype","type":"COMBO","widget":{"name":"weight_dtype"},"link":null}],"outputs":[{"localized_name":"MODÈLE","name":"MODEL","type":"MODEL","links":[53]}],"properties":{"Node name for S&R":"UNETLoader","enableTabs":false,"tabWidth":65,"tabXOffset":10,"hasSecondTab":false,"secondTabText":"Send Back","secondTabOffset":80,"secondTabWidth":65,"cnr_id":"comfy-core","ver":"0.5.1","models":[{"name":"NewBie-Image-Exp0.1-bf16.safetensors","url":"https://huggingface.co/Comfy-Org/NewBie-image-Exp0.1_repackaged/resolve/main/split_files/diffusion_models/NewBie-Image-Exp0.1-bf16.safetensors","directory":"diffusion_models"}]},"widgets_values":["NewBie-Image-Exp0.1-bf16.safetensors","default"]},{"id":26,"type":"VAELoader","pos":[-90,380],"size":[370,58],"flags":{},"order":1,"mode":0,"inputs":[{"localized_name":"nom_vae","name":"vae_name","type":"COMBO","widget":{"name":"vae_name"},"link":null}],"outputs":[{"localized_name":"VAE","name":"VAE","type":"VAE","links":[42]}],"properties":{"Node name for S&R":"VAELoader","enableTabs":false,"tabWidth":65,"tabXOffset":10,"hasSecondTab":false,"secondTabText":"Send Back","secondTabOffset":80,"secondTabWidth":65,"cnr_id":"comfy-core","ver":"0.5.1","models":[{"name":"ae.safetensors","url":"https://huggingface.co/Comfy-Org/z_image_turbo/resolve/main/split_files/vae/ae.safetensors","directory":"vae"}]},"widgets_values":["ae.safetensors"]},{"id":34,"type":"DualCLIPLoader","pos":[-90,200],"size":[370,130],"flags":{},"order":2,"mode":0,"inputs":[{"localized_name":"nom_clip1","name":"clip_name1","type":"COMBO","widget":{"name":"clip_name1"},"link":null},{"localized_name":"nom_clip2","name":"clip_name2","type":"COMBO","widget":{"name":"clip_name2"},"link":null},{"localized_name":"type","name":"type","type":"COMBO","widget":{"name":"type"},"link":null},{"localized_name":"appareil","name":"device","shape":7,"type":"COMBO","widget":{"name":"device"},"link":null}],"outputs":[{"localized_name":"CLIP","name":"CLIP","type":"CLIP","links":[70,77]}],"properties":{"Node name for S&R":"DualCLIPLoader","enableTabs":false,"tabWidth":65,"tabXOffset":10,"hasSecondTab":false,"secondTabText":"Send Back","secondTabOffset":80,"secondTabWidth":65,"cnr_id":"comfy-core","ver":"0.5.1","models":[{"name":"gemma_3_4b_it_bf16.safetensors","url":"https://huggingface.co/Comfy-Org/NewBie-image-Exp0.1_repackaged/resolve/main/split_files/text_encoders/gemma_3_4b_it_bf16.safetensors","directory":"text_encoders"},{"name":"jina_clip_v2_bf16.safetensors","url":"https://huggingface.co/Comfy-Org/NewBie-image-Exp0.1_repackaged/resolve/main/split_files/text_encoders/jina_clip_v2_bf16.safetensors","directory":"text_encoders"}]},"widgets_values":["gemma_3_4b_it_bf16.safetensors","jina_clip_v2_bf16.safetensors","newbie","default"]},{"id":8,"type":"VAEDecode","pos":[1150,190],"size":[151.13671875,46],"flags":{},"order":6,"mode":0,"inputs":[{"localized_name":"échantillons","name":"samples","type":"LATENT","link":7},{"localized_name":"vae","name":"vae","type":"VAE","link":42}],"outputs":[{"localized_name":"IMAGE","name":"IMAGE","type":"IMAGE","slot_index":0,"links":[9]}],"properties":{"Node name for S&R":"VAEDecode","enableTabs":false,"tabWidth":65,"tabXOffset":10,"hasSecondTab":false,"secondTabText":"Send Back","secondTabOffset":80,"secondTabWidth":65,"cnr_id":"comfy-core","ver":"0.5.1"},"widgets_values":[]},{"id":31,"type":"EmptySD3LatentImage","pos":[-90,500],"size":[270,106],"flags":{},"order":3,"mode":0,"inputs":[{"localized_name":"largeur","name":"width","type":"INT","widget":{"name":"width"},"link":null},{"localized_name":"hauteur","name":"height","type":"INT","widget":{"name":"height"},"link":null},{"localized_name":"taille_du_lot","name":"batch_size","type":"INT","widget":{"name":"batch_size"},"link":null}],"outputs":[{"localized_name":"LATENT","name":"LATENT","type":"LATENT","links":[48]}],"properties":{"Node name for S&R":"EmptySD3LatentImage","enableTabs":false,"tabWidth":65,"tabXOffset":10,"hasSecondTab":false,"secondTabText":"Send Back","secondTabOffset":80,"secondTabWidth":65,"cnr_id":"comfy-core","ver":"0.5.1"},"widgets_values":[1024,1536,1]},{"id":3,"type":"KSampler","pos":[810,190],"size":[310,474],"flags":{},"order":5,"mode":0,"inputs":[{"localized_name":"model","name":"model","type":"MODEL","link":50},{"localized_name":"positive","name":"positive","type":"CONDITIONING","link":73},{"localized_name":"negative","name":"negative","type":"CONDITIONING","link":80},{"localized_name":"latent_image","name":"latent_image","type":"LATENT","link":48},{"localized_name":"seed","name":"seed","type":"INT","widget":{"name":"seed"},"link":null},{"localized_name":"steps","name":"steps","type":"INT","widget":{"name":"steps"},"link":null},{"localized_name":"cfg","name":"cfg","type":"FLOAT","widget":{"name":"cfg"},"link":null},{"localized_name":"sampler_name","name":"sampler_name","type":"COMBO","widget":{"name":"sampler_name"},"link":null},{"localized_name":"scheduler","name":"scheduler","type":"COMBO","widget":{"name":"scheduler"},"link":null},{"localized_name":"denoise","name":"denoise","type":"FLOAT","widget":{"name":"denoise"},"link":null}],"outputs":[{"localized_name":"LATENT","name":"LATENT","type":"LATENT","slot_index":0,"links":[7]}],"properties":{"Node name for S&R":"KSampler","enableTabs":false,"tabWidth":65,"tabXOffset":10,"hasSecondTab":false,"secondTabText":"Send Back","secondTabOffset":80,"secondTabWidth":65,"cnr_id":"comfy-core","ver":"0.5.1"},"widgets_values":[27582042565232,"fixed",20,5.5,"res_multistep","simple",1]},{"id":43,"type":"CLIPTextEncode","pos":[340,80],"size":[440,170],"flags":{},"order":7,"mode":0,"inputs":[{"localized_name":"clip","name":"clip","type":"CLIP","link":70},{"localized_name":"text","name":"text","type":"STRING","widget":{"name":"text"},"link":86}],"outputs":[{"localized_name":"CONDITIONNEMENT","name":"CONDITIONING","type":"CONDITIONING","slot_index":0,"links":[73]}],"title":"CLIP Text Encode (Positive Prompt)","properties":{"Node name for S&R":"CLIPTextEncode","enableTabs":false,"tabWidth":65,"tabXOffset":10,"hasSecondTab":false,"secondTabText":"Send Back","secondTabOffset":80,"secondTabWidth":65,"cnr_id":"comfy-core","ver":"0.5.1"},"widgets_values":[""],"color":"#232","bgcolor":"#353"},{"id":49,"type":"CLIPTextEncode","pos":[340,330],"size":[440,170],"flags":{},"order":8,"mode":0,"inputs":[{"localized_name":"clip","name":"clip","type":"CLIP","link":77},{"localized_name":"text","name":"text","type":"STRING","widget":{"name":"text"},"link":87}],"outputs":[{"localized_name":"CONDITIONNEMENT","name":"CONDITIONING","type":"CONDITIONING","slot_index":0,"links":[80]}],"title":"CLIP Text Encode (Negative Prompt)","properties":{"Node name for S&R":"CLIPTextEncode","enableTabs":false,"tabWidth":65,"tabXOffset":10,"hasSecondTab":false,"secondTabText":"Send Back","secondTabOffset":80,"secondTabWidth":65,"cnr_id":"comfy-core","ver":"0.5.1"},"widgets_values":["You are an assistant designed to generate low-quality images based on textual prompts. <Prompt Start>"],"color":"#223","bgcolor":"#335"}],"groups":[],"links":[{"id":53,"origin_id":30,"origin_slot":0,"target_id":32,"target_slot":0,"type":"MODEL"},{"id":7,"origin_id":3,"origin_slot":0,"target_id":8,"target_slot":0,"type":"LATENT"},{"id":42,"origin_id":26,"origin_slot":0,"target_id":8,"target_slot":1,"type":"VAE"},{"id":50,"origin_id":32,"origin_slot":0,"target_id":3,"target_slot":0,"type":"MODEL"},{"id":48,"origin_id":31,"origin_slot":0,"target_id":3,"target_slot":3,"type":"LATENT"},{"id":9,"origin_id":8,"origin_slot":0,"target_id":-20,"target_slot":0,"type":"IMAGE"},{"id":70,"origin_id":34,"origin_slot":0,"target_id":43,"target_slot":0,"type":"CLIP"},{"id":73,"origin_id":43,"origin_slot":0,"target_id":3,"target_slot":1,"type":"CONDITIONING"},{"id":77,"origin_id":34,"origin_slot":0,"target_id":49,"target_slot":0,"type":"CLIP"},{"id":80,"origin_id":49,"origin_slot":0,"target_id":3,"target_slot":2,"type":"CONDITIONING"},{"id":86,"origin_id":-10,"origin_slot":0,"target_id":43,"target_slot":1,"type":"STRING"},{"id":87,"origin_id":-10,"origin_slot":1,"target_id":49,"target_slot":1,"type":"STRING"}],"extra":{"workflowRendererVersion":"LG"}}]},"config":{},"extra":{"frontendVersion":"1.36.6","workflowRendererVersion":"LG","VHS_latentpreview":false,"VHS_latentpreviewrate":0,"VHS_MetadataImage":true,"VHS_KeepIntermediate":true,"ds":{"scale":0.3498530083509863,"offset":[2609.535508299993,1127.6371119322107]}},"version":0.4}